gprof_nn/__init__.py
gprof_nn/augmentation.py
gprof_nn/coordinates.py
gprof_nn/definitions.py
gprof_nn/legacy.py
gprof_nn/logging.py
gprof_nn/models.py
gprof_nn/normalizer.py
gprof_nn/plotting.py
gprof_nn/resolution.py
gprof_nn/retrieval.py
gprof_nn/sensors.py
gprof_nn/statistics.py
gprof_nn/utils.py
gprof_nn/validation.py
gprof_nn/version.py
gprof_nn/bin/__init__.py
gprof_nn/bin/combine_validation_data.py
gprof_nn/bin/extract_data.py
gprof_nn/bin/extract_validation_data.py
gprof_nn/bin/legacy.py
gprof_nn/bin/process.py
gprof_nn/bin/retrieve.py
gprof_nn/bin/run_preprocessor.py
gprof_nn/bin/statistics.py
gprof_nn/bin/train.py
gprof_nn/data/__init__.py
gprof_nn/data/bin.py
gprof_nn/data/cdf.py
gprof_nn/data/combined.py
gprof_nn/data/kwaj.py
gprof_nn/data/l1c.py
gprof_nn/data/mrms.py
gprof_nn/data/preprocessor.py
gprof_nn/data/profiles.py
gprof_nn/data/retrieval.py
gprof_nn/data/sim.py
gprof_nn/data/surface.py
gprof_nn/data/training_data.py
gprof_nn/data/types.py
gprof_nn/data/utils.py
gprof_nn/data/validation.py
gprof_nn/files/gmi_era5_sensitivities.npy
gprof_nn/files/matplotlib_style.rc
gprof_nn/files/normalizer_gmi.pckl
gprof_nn/files/preprocessor_template.pp
gprof_nn-0.1.dist-info/LICENSE
gprof_nn-0.1.dist-info/METADATA
gprof_nn-0.1.dist-info/WHEEL
gprof_nn-0.1.dist-info/entry_points.txt
gprof_nn-0.1.dist-info/top_level.txt
gprof_nn-0.1.dist-info/RECORD
